ECAUGT/ECAUGT.py
ECAUGT/__init__.py
ECAUGT/uhafOBO_0621.csv
ECAUGT-1.0.6.dist-info/METADATA
ECAUGT-1.0.6.dist-info/WHEEL
ECAUGT-1.0.6.dist-info/top_level.txt
ECAUGT-1.0.6.dist-info/RECORD
