Metadata-Version: 2.1
Name: ECAUGT
Version: 1.0.6
Summary: ECA Client
Home-page: UNKNOWN
Author: Yixin Chen & Haiyang Bian
Author-email: chenyx19@mails.tsinghua.edu.cn
Maintainer: Minsheng Hao
Maintainer-email: hmsh653@gmail.com
License: UNKNOWN
Keywords: Client,ECA
Platform: UNKNOWN
Requires-Python: >=3
Requires-Dist: tablestore (>=5.2.1)
Requires-Dist: numpy
Requires-Dist: pandas
